README.txt
setup.cfg
setup.py
docs/HISTORY.txt
raptus/__init__.py
raptus.contentflow.egg-info/PKG-INFO
raptus.contentflow.egg-info/SOURCES.txt
raptus.contentflow.egg-info/dependency_links.txt
raptus.contentflow.egg-info/entry_points.txt
raptus.contentflow.egg-info/namespace_packages.txt
raptus.contentflow.egg-info/not-zip-safe
raptus.contentflow.egg-info/requires.txt
raptus.contentflow.egg-info/top_level.txt
raptus/contentflow/__init__.py
raptus/contentflow/configure.zcml
raptus/contentflow/interfaces.py
raptus/contentflow/properties.py
raptus/contentflow/providers.py
raptus/contentflow/browser/__init__.py
raptus/contentflow/browser/configure.zcml
raptus/contentflow/browser/contentflow.pt
raptus/contentflow/browser/contentflow.py
raptus/contentflow/browser/xml.py
raptus/contentflow/browser/flash/contentflow.swf
raptus/contentflow/browser/flash/fla/Coverflow.as
raptus/contentflow/browser/flash/fla/CoverflowItem.as
raptus/contentflow/browser/flash/fla/CoverflowItemEvent.as
raptus/contentflow/browser/flash/fla/Main.as
raptus/contentflow/browser/flash/fla/Main.fla
raptus/contentflow/browser/flash/fla/Reflect.as
raptus/contentflow/browser/flash/fla/Scrollbar.as
raptus/contentflow/browser/flash/fla/ScrollbarEvent.as
raptus/contentflow/browser/flash/fla/com/greensock/OverwriteManager.as
raptus/contentflow/browser/flash/fla/com/greensock/TimelineLite.as
raptus/contentflow/browser/flash/fla/com/greensock/TimelineMax.as
raptus/contentflow/browser/flash/fla/com/greensock/TweenAlign.as
raptus/contentflow/browser/flash/fla/com/greensock/TweenLite.as
raptus/contentflow/browser/flash/fla/com/greensock/TweenMax.as
raptus/contentflow/browser/flash/fla/com/greensock/TweenNano.as
raptus/contentflow/browser/flash/fla/com/greensock/changelog.txt
raptus/contentflow/browser/flash/fla/com/greensock/core/PropTween.as
raptus/contentflow/browser/flash/fla/com/greensock/core/SimpleTimeline.as
raptus/contentflow/browser/flash/fla/com/greensock/core/TweenCore.as
raptus/contentflow/browser/flash/fla/com/greensock/data/BevelFilterVars.as
raptus/contentflow/browser/flash/fla/com/greensock/data/BlurFilterVars.as
raptus/contentflow/browser/flash/fla/com/greensock/data/ColorMatrixFilterVars.as
raptus/contentflow/browser/flash/fla/com/greensock/data/ColorTransformVars.as
