Metadata-Version: 1.0
Name: raptus.contentflow
Version: 1.0b2
Summary: Provides a view for folders and collections which shows the contents in a ContentFlow
Home-page: http://raptus.com
Author: Raptus AG
Author-email: dev@raptus.com
License: GPL
Platform: UNKNOWN
Classifier: Programming Language :: Python
Classifier: Topic :: Software Development :: Libraries :: Python Modules
